{
    "percentage_bucket_counter_full": {
        "rest": 100.0,
        "5": 4.3478260869565215,
        "10": 8.695652173913043,
        "15": 8.695652173913043,
        "20": 8.695652173913043
    },
    "percentage_bucket_counter_generic": {
        "rest": 100.0,
        "5": 4.3478260869565215,
        "10": 8.695652173913043,
        "15": 8.695652173913043,
        "20": 8.695652173913043
    },
    "mean_budget_generic": 84.42057755470978,
    "mean_add_points_generic": 120.0,
    "nr_func_modeled_generic": 23,
    "percentage_bucket_counter_gpr": {
        "rest": 100.0,
        "5": 4.3478260869565215,
        "10": 8.695652173913043,
        "15": 8.695652173913043,
        "20": 8.695652173913043
    },
    "mean_add_points_gpr": 123.04347826086956,
    "mean_budget_gpr": 93.94314803521215,
    "nr_func_modeled_gpr": 23,
    "percentage_bucket_counter_hybrid": {
        "rest": 100.0,
        "5": 4.3478260869565215,
        "10": 8.695652173913043,
        "15": 8.695652173913043,
        "20": 8.695652173913043
    },
    "mean_budget_hybrid": 93.83925520373872,
    "mean_add_points_hybrid": 123.04347826086956,
    "nr_func_modeled_hybrid": 23,
    "base_point_cost": 5.139588058508245,
    "min_points": 9,
    "budget": 96
}